{
  "_class": "shapeGroup",
  "clippingMaskMode": 0,
  "do_objectID": "56F2EF6A-C653-4372-BE40-58B2FD0C1005",
  "exportOptions": {
    "_class": "exportOptions",
    "do_objectID": "3D24544A-5070-4310-A145-0E0B148472F7",
    "exportFormats": [
    ],
    "includedLayerIds": [
    ],
    "layerOptions": 0,
    "shouldTrim": false
  },
  "frame": {
    "_class": "rect",
    "constrainProportions": false,
    "do_objectID": "F2982581-FEE0-408B-A195-353731BC5EF1",
    "height": 5.714595478448881,
    "width": 2.845136015179709,
    "x": 6.267153289203634,
    "y": 2.138112554964579
  },
  "hasClickThrough": false,
  "hasClippingMask": false,
  "isFlippedHorizontal": false,
  "isFlippedVertical": false,
  "isLocked": false,
  "isVisible": true,
  "layerListExpandedType": 1,
  "layers": [
    {
      "class": "shapePath",
      "id": "D574836D-257D-4E49-AD6C-8D7579412F76"
    }
  ],
  "name": "Shape",
  "nameIsFixed": false,
  "resizingConstraint": 63,
  "resizingType": 0,
  "rotation": 0,
  "shouldBreakMaskChain": false,
  "style": {
    "_class": "style",
    "do_objectID": "D3D4487B-DBB7-49AB-B633-E7F5EC92A23F",
    "endDecorationType": 0,
    "fills": [
      {
        "_class": "fill",
        "color": {
          "_class": "color",
          "alpha": 1,
          "blue": 0,
          "green": 0,
          "red": 0
        },
        "fillType": 0,
        "isEnabled": true,
        "noiseIndex": 0,
        "noiseIntensity": 0,
        "patternFillType": 1,
        "patternTileScale": 1
      }
    ],
    "miterLimit": 10,
    "startDecorationType": 0
  },
  "windingRule": 0
}